rustest-0.16.1.dist-info/METADATA
rustest-0.16.1.dist-info/WHEEL
rustest-0.16.1.dist-info/entry_points.txt
rustest-0.16.1.dist-info/licenses/LICENSE
rustest/__init__.py
rustest/__main__.py
rustest/approx.py
rustest/async_executor.py
rustest/builtin_fixtures.py
rustest/cli.py
rustest/compat/__init__.py
rustest/compat/pytest.py
rustest/compat/pytest_asyncio.py
rustest/core.py
rustest/decorators.py
rustest/event_router.py
rustest/fixture_registry.py
rustest/py.typed
rustest/renderers/__init__.py
rustest/renderers/rich_renderer.py
rustest/reporting.py
rustest/rust.cp310-win_amd64.pyd
rustest/rust.py
rustest/rust.pyi
rustest-0.16.1.dist-info/RECORD
