Metadata-Version: 2.4
Name: rustest
Version: 0.16.1
Classifier: Development Status :: 3 - Alpha
Classifier: Intended Audience :: Developers
Classifier: License :: OSI Approved :: MIT License
Classifier: Programming Language :: Python :: 3
Classifier: Programming Language :: Python :: 3.10
Classifier: Programming Language :: Python :: 3.11
Classifier: Programming Language :: Python :: 3.12
Classifier: Programming Language :: Python :: 3.13
Classifier: Programming Language :: Python :: 3.14
Classifier: Programming Language :: Rust
Classifier: Topic :: Software Development :: Testing
Requires-Dist: typing-extensions>=4.15
Requires-Dist: rich>=13.0.0
Requires-Dist: basedpyright>=1.19 ; extra == 'dev'
Requires-Dist: maturin>=1.4,<2 ; extra == 'dev'
Requires-Dist: packaging>=20.0 ; extra == 'dev'
Requires-Dist: poethepoet>=0.22 ; extra == 'dev'
Requires-Dist: pre-commit>=3.5 ; extra == 'dev'
Requires-Dist: py>=1.11 ; extra == 'dev'
Requires-Dist: pytest>=7.0 ; extra == 'dev'
Requires-Dist: pytest-asyncio>=1.2.0 ; extra == 'dev'
Requires-Dist: pytest-codeblocks>=0.17.0 ; extra == 'dev'
Requires-Dist: ruff>=0.1.9 ; extra == 'dev'
Requires-Dist: zensical ; extra == 'docs'
Provides-Extra: dev
Provides-Extra: docs
License-File: LICENSE
Summary: Rust powered pytest-compatible runner
Author: rustest contributors
Requires-Python: >=3.10
Project-URL: Homepage, https://github.com/Apex-Engineers-Inc/rustest
Project-URL: Repository, https://github.com/Apex-Engineers-Inc/rustest
Project-URL: Documentation, https://apex-engineers-inc.github.io/rustest
